{"get":"fixtures","parameters":{"team":"532","season":"2025","last":"5","league":"140"},"errors":[],"results":5,"paging":{"current":1,"total":1},"response":[{"fixture":{"id":1391078,"referee":"Adrian Cordero Vega, Spain","timezone":"UTC","date":"2026-03-01T15:15:00+00:00","timestamp":1772378100,"periods":{"first":1772378100,"second":1772381700},"venue":{"id":1497,"name":"Estadio de Mestalla","city":"Valencia"},"status":{"long":"Match Finished","short":"FT","elapsed":90,"extra":10}},"league":{"id":140,"name":"La Liga","country":"Spain","logo":"https:\/\/media.api-sports.io\/football\/leagues\/140.png","flag":"https:\/\/media.api-sports.io\/flags\/es.svg","season":2025,"round":"Regular Season - 26","standings":true},"teams":{"home":{"id":532,"name":"Valencia","logo":"https:\/\/media.api-sports.io\/football\/teams\/532.png","winner":true},"away":{"id":727,"name":"Osasuna","logo":"https:\/\/media.api-sports.io\/football\/teams\/727.png","winner":false}},"goals":{"home":1,"away":0},"score":{"halftime":{"home":0,"away":0},"fulltime":{"home":1,"away":0},"extratime":{"home":null,"away":null},"penalty":{"home":null,"away":null}}},{"fixture":{"id":1391068,"referee":"Jesus Gil Manzano, Spain","timezone":"UTC","date":"2026-02-22T20:00:00+00:00","timestamp":1771790400,"periods":{"first":1771790400,"second":1771794000},"venue":{"id":1498,"name":"Estadio de la Ceramica","city":"Villarreal"},"status":{"long":"Match Finished","short":"FT","elapsed":90,"extra":4}},"league":{"id":140,"name":"La Liga","country":"Spain","logo":"https:\/\/media.api-sports.io\/football\/leagues\/140.png","flag":"https:\/\/media.api-sports.io\/flags\/es.svg","season":2025,"round":"Regular Season - 25","standings":true},"teams":{"home":{"id":533,"name":"Villarreal","logo":"https:\/\/media.api-sports.io\/football\/teams\/533.png","winner":true},"away":{"id":532,"name":"Valencia","logo":"https:\/\/media.api-sports.io\/football\/teams\/532.png","winner":false}},"goals":{"home":2,"away":1},"score":{"halftime":{"home":2,"away":1},"fulltime":{"home":2,"away":1},"extratime":{"home":null,"away":null},"penalty":{"home":null,"away":null}}},{"fixture":{"id":1391053,"referee":"Miguel Angel Ortiz Arias, Spain","timezone":"UTC","date":"2026-02-15T17:30:00+00:00","timestamp":1771176600,"periods":{"first":1771176600,"second":1771180200},"venue":{"id":1482,"name":"Estadio Ciudad de Valencia","city":"Valencia"},"status":{"long":"Match Finished","short":"FT","elapsed":90,"extra":9}},"league":{"id":140,"name":"La Liga","country":"Spain","logo":"https:\/\/media.api-sports.io\/football\/leagues\/140.png","flag":"https:\/\/media.api-sports.io\/flags\/es.svg","season":2025,"round":"Regular Season - 24","standings":true},"teams":{"home":{"id":539,"name":"Levante","logo":"https:\/\/media.api-sports.io\/football\/teams\/539.png","winner":false},"away":{"id":532,"name":"Valencia","logo":"https:\/\/media.api-sports.io\/football\/teams\/532.png","winner":true}},"goals":{"home":0,"away":2},"score":{"halftime":{"home":0,"away":0},"fulltime":{"home":0,"away":2},"extratime":{"home":null,"away":null},"penalty":{"home":null,"away":null}}},{"fixture":{"id":1391047,"referee":"Javier Alberola Rojas, Spain","timezone":"UTC","date":"2026-02-08T20:00:00+00:00","timestamp":1770580800,"periods":{"first":1770580800,"second":1770584400},"venue":{"id":1497,"name":"Estadio de Mestalla","city":"Valencia"},"status":{"long":"Match Finished","short":"FT","elapsed":90,"extra":6}},"league":{"id":140,"name":"La Liga","country":"Spain","logo":"https:\/\/media.api-sports.io\/football\/leagues\/140.png","flag":"https:\/\/media.api-sports.io\/flags\/es.svg","season":2025,"round":"Regular Season - 23","standings":true},"teams":{"home":{"id":532,"name":"Valencia","logo":"https:\/\/media.api-sports.io\/football\/teams\/532.png","winner":false},"away":{"id":541,"name":"Real Madrid","logo":"https:\/\/media.api-sports.io\/football\/teams\/541.png","winner":true}},"goals":{"home":0,"away":2},"score":{"halftime":{"home":0,"away":0},"fulltime":{"home":0,"away":2},"extratime":{"home":null,"away":null},"penalty":{"home":null,"away":null}}},{"fixture":{"id":1391030,"referee":"José María Sánchez Martínez, Spain","timezone":"UTC","date":"2026-02-01T15:15:00+00:00","timestamp":1769958900,"periods":{"first":1769958900,"second":1769962500},"venue":{"id":null,"name":"Estadio de la Cartuja","city":"Seville"},"status":{"long":"Match Finished","short":"FT","elapsed":90,"extra":7}},"league":{"id":140,"name":"La Liga","country":"Spain","logo":"https:\/\/media.api-sports.io\/football\/leagues\/140.png","flag":"https:\/\/media.api-sports.io\/flags\/es.svg","season":2025,"round":"Regular Season - 22","standings":true},"teams":{"home":{"id":543,"name":"Real Betis","logo":"https:\/\/media.api-sports.io\/football\/teams\/543.png","winner":true},"away":{"id":532,"name":"Valencia","logo":"https:\/\/media.api-sports.io\/football\/teams\/532.png","winner":false}},"goals":{"home":2,"away":1},"score":{"halftime":{"home":1,"away":1},"fulltime":{"home":2,"away":1},"extratime":{"home":null,"away":null},"penalty":{"home":null,"away":null}}}]}